scipy_data_fitting/__init__.py
scipy_data_fitting/core.py
scipy_data_fitting/data.py
scipy_data_fitting/fit.py
scipy_data_fitting/model.py
scipy_data_fitting/plot.py
scipy_data_fitting/version.py
scipy_data_fitting/figure/__init__.py
scipy_data_fitting/figure/fit.py
scipy_data_fitting/figure/plot.py
scipy_data_fitting-1.0.2.dist-info/DESCRIPTION.rst
scipy_data_fitting-1.0.2.dist-info/METADATA
scipy_data_fitting-1.0.2.dist-info/RECORD
scipy_data_fitting-1.0.2.dist-info/WHEEL
scipy_data_fitting-1.0.2.dist-info/metadata.json
scipy_data_fitting-1.0.2.dist-info/top_level.txt
