Metadata-Version: 1.0
Name: scipy-data_fitting
Version: 1.0.2
Summary: Complete pipeline for easy data fitting with Python.
Home-page: https://github.com/razor-x/scipy-data_fitting
Author: Evan Sosenko
Author-email: razorx@evansosenko.com
License: MIT
Platform: UNKNOWN
